README.md
setup.cfg
setup.py
src/sparkd/__init__.py
src/sparkd/daemon.py
src/sparkd/logger.py
src/sparkd/main.py
src/sparkd/process.py
src/sparkd/sparkd.py
src/sparkd/supervisor.py
src/sparkd.egg-info/PKG-INFO
src/sparkd.egg-info/SOURCES.txt
src/sparkd.egg-info/dependency_links.txt
src/sparkd.egg-info/entry_points.txt
src/sparkd.egg-info/requires.txt
src/sparkd.egg-info/top_level.txt