Metadata-Version: 2.1
Name: sparkd
Version: 0.0.1b0
Summary: Spark Networks DevOps coding challenge
Home-page: https://gitlab.com/askainet/spark-networks-code-challenge
Author: Ivan Lopez
Author-email: ivan@askai.net
License: UNKNOWN
Platform: UNKNOWN
Classifier: License :: OSI Approved :: MIT License
Classifier: Programming Language :: Python :: 3.4
Classifier: Programming Language :: Python :: 3.5
Classifier: Programming Language :: Python :: 3.6
Classifier: Programming Language :: Python :: 3.7
Classifier: Operating System :: POSIX
Requires-Python: >=3.4, <4
Provides-Extra: dev
